{
	"configurations" : 
	[
		{
			"directories" : 
			[
				{
					"build" : ".",
					"jsonFile" : "directory-.-Debug-d0094a50bb2071803777.json",
					"minimumCMakeVersion" : 
					{
						"string" : "3.25"
					},
					"projectIndex" : 0,
					"source" : ".",
					"targetIndexes" : 
					[
						0
					]
				}
			],
			"name" : "Debug",
			"projects" : 
			[
				{
					"directoryIndexes" : 
					[
						0
					],
					"name" : "Tarea_2___CLION",
					"targetIndexes" : 
					[
						0
					]
				}
			],
			"targets" : 
			[
				{
					"directoryIndex" : 0,
					"id" : "Tarea_2___CLION::@6890427a1f51a3e7e1df",
					"jsonFile" : "target-Tarea_2___CLION-Debug-9113cae969c4cec3b0e3.json",
					"name" : "Tarea_2___CLION",
					"projectIndex" : 0
				}
			]
		}
	],
	"kind" : "codemodel",
	"paths" : 
	{
		"build" : "C:/Users/Ricardo/Documents/00831/Tarea 2 - CLION/cmake-build-debug",
		"source" : "C:/Users/Ricardo/Documents/00831/Tarea 2 - CLION"
	},
	"version" : 
	{
		"major" : 2,
		"minor" : 4
	}
}
